pymicroconf/__init__.py
pymicroconf/config_handler.py
pymicroconf/exceptions.py
pymicroconf/types.py
pymicroconf-0.1.0.dist-info/METADATA
pymicroconf-0.1.0.dist-info/WHEEL
pymicroconf-0.1.0.dist-info/licenses/LICENSE
pymicroconf-0.1.0.dist-info/RECORD
