Metadata-Version: 2.4
Name: pymicroconf
Version: 0.1.0
Summary: A Python library for managing configuration files using TOML and environment variables
Project-URL: Homepage, https://github.com/NickBrisebois/pymicroconf
Project-URL: Source, https://github.com/NickBrisebois/pymicroconf
Project-URL: Tracker, https://github.com/NickBrisebois/pymicroconf/issues
Author-email: Nick Brisebois <email@nick-b.ca>
Maintainer-email: Nick Brisebois <email@nick-b.ca>
License: MIT License
License-File: LICENSE
Keywords: config,configuration,dataclass,environment,environment variables,settings,toml
Classifier: Development Status :: 4 - Beta
Classifier: Intended Audience :: Developers
Classifier: License :: OSI Approved :: MIT License
Classifier: Operating System :: OS Independent
Classifier: Programming Language :: Python :: 3
Classifier: Programming Language :: Python :: 3.11
Classifier: Programming Language :: Python :: 3.12
Classifier: Programming Language :: Python :: 3.13
Classifier: Topic :: Software Development :: Libraries :: Python Modules
Classifier: Topic :: System :: Systems Administration
Classifier: Topic :: Utilities
Requires-Python: >=3.12
